kubecrd/__init__.py
kubecrd/schemabase.py
kubecrd-0.5.0.dist-info/LICENSE
kubecrd-0.5.0.dist-info/WHEEL
kubecrd-0.5.0.dist-info/METADATA
kubecrd-0.5.0.dist-info/RECORD
