Metadata-Version: 2.1
Name: kubecrd
Version: 0.5.0
Summary: Create Kubernetes CRD using Python dataclasses
Home-page: https://github.com/maxking/kubecrd
License: Apache-2.0
Author: Abhilash Raj
Author-email: raj.abhilash1@gmail.com
Requires-Python: >=3.7,<4
Classifier: License :: OSI Approved :: Apache Software License
Classifier: Programming Language :: Python :: 3
Classifier: Programming Language :: Python :: 3.10
Classifier: Programming Language :: Python :: 3.7
Classifier: Programming Language :: Python :: 3.8
Classifier: Programming Language :: Python :: 3.9
Requires-Dist: PyYAML (>=6.0)
Requires-Dist: apischema (>=0.15.0)
Requires-Dist: kubernetes (>=23.3.0,<24.0.0)
Project-URL: Bug Tracker, https://github.com/maxking/kubecrd/issues
Project-URL: Repository, https://github.com/maxking/kubecrd
